recordflow/__init__.py
recordflow/api.py
recordflow/cli.py
recordflow/config.py
recordflow/optimization.py
recordflow/recording.py
recordflow-0.1.0.dist-info/METADATA
recordflow-0.1.0.dist-info/WHEEL
recordflow-0.1.0.dist-info/entry_points.txt
recordflow-0.1.0.dist-info/top_level.txt
recordflow-0.1.0.dist-info/RECORD
