Metadata-Version: 2.4
Name: recordflow
Version: 0.1.0
Summary: Segmented screen recording helpers built on ffmpeg.
Author: Jonathan
Classifier: Programming Language :: Python :: 3
Classifier: Programming Language :: Python :: 3 :: Only
Classifier: Operating System :: MacOS :: MacOS X
Classifier: Topic :: Multimedia :: Video :: Capture
Requires-Python: >=3.9
